<?xml version="1.0" encoding="UTF-8"?>
<tv generator-info-name="WebGrab+Plus/w MDB &amp; REX Postprocess -- version  V3.0.0.0 -- build 3 -- Jan van Straaten" generator-info-url="http://www.webgrabplus.com">
  <channel id="StayAtHome TV">
    <display-name lang="en">StayAtHome TV</display-name>
    <icon src="https://seeklogo.com/images/S/stay-home-logo-616E3197E7-seeklogo.com.png" />
    <url>http://www.google.com</url>
  </channel>
  <programme start="20201201173000 -0500" stop="20201201192900 -0500" channel="StayAtHome TV">
    <title lang="en">Skin (2018)</title>
    <desc lang="en">A destitute young man, raised by racist skinheads and notorious among white supremacists, turns his back on hatred and violence to transform his life, with the help of a black activist and the woman he loves</desc>
    <category lang="en">Crime</category>
    <icon src="https://m.media-amazon.com/images/M/MV5BNmFiZjA2ZDEtMTk5NC00MTZkLTgxYTEtMjFmOGI4OTVmNmEwXkEyXkFqcGdeQXVyODQyNzE3MDg@._V1_UX182_CR0,0,182,268_AL_.jpg" />
  </programme>
  <programme start="20201201192901 -0500" stop="20201201211300 -0500" channel="StayAtHome TV">
    <title lang="en">The Disaster Artist (2017)</title>
    <desc lang="en"></desc>
    <category lang="en">Biography, Comedy</category>
    <icon src="https://m.media-amazon.com/images/M/MV5BOGNkMzliMGMtMDI5Ni00OTZkLTgyMTYtNzk5ZTY1NjVhYjVmXkEyXkFqcGdeQXVyNTAzMTY4MDA@._V1_UX182_CR0,0,182,268_AL_.jpg" />
  </programme>
  <programme start="20201201211301 -0500" stop="20201201232800 -0500" channel="StayAtHome TV">
    <title lang="en">Roma (2018)</title>
    <desc lang="en">A year in the life of a middle-class family's maid in Mexico City in the early 1970s</desc>
    <category lang="en">Drama</category>
    <icon src="https://m.media-amazon.com/images/M/MV5BMTU0OTc3ODk4Ml5BMl5BanBnXkFtZTgwMzM4NzI5NjM@._V1_UX182_CR0,0,182,268_AL_.jpg" />
  </programme>
  <programme start="20201201232801 -0500" stop="20201202010100 -0500" channel="StayAtHome TV">
    <title lang="en">The Old Man & the Gun (2018)</title>
    <desc lang="en">Based on the true story of Forrest Tucker and his audacious escape from San Quentin at the age of 70 to an unprecedented string of heists that confounded authorities and enchanted the public</desc>
    <category lang="en">Biography, Crime</category>
    <icon src="https://m.media-amazon.com/images/M/MV5BOTk3NjU5MjIxM15BMl5BanBnXkFtZTgwNjU0OTU2NTM@._V1_UX182_CR0,0,182,268_AL_.jpg" />
  </programme>
  <programme start="20201202010101 -0500" stop="20201202030000 -0500" channel="StayAtHome TV">
    <title lang="en">Skin (2018)</title>
    <desc lang="en">A destitute young man, raised by racist skinheads and notorious among white supremacists, turns his back on hatred and violence to transform his life, with the help of a black activist and the woman he loves</desc>
    <category lang="en">Crime</category>
    <icon src="https://m.media-amazon.com/images/M/MV5BNmFiZjA2ZDEtMTk5NC00MTZkLTgxYTEtMjFmOGI4OTVmNmEwXkEyXkFqcGdeQXVyODQyNzE3MDg@._V1_UX182_CR0,0,182,268_AL_.jpg" />
  </programme>
  <programme start="20201202030001 -0500" stop="20201202170000 -0500" channel="StayAtHome TV">
    <title lang="en">\\ REPEAT or OFFLINE//</title>
    <desc lang="en"></desc>
    <category lang="en"></category>
    <icon src="https://seeklogo.com/images/S/stay-home-logo-616E3197E7-seeklogo.com.png" />
  </programme>
 </tv>